{
  "id": "rf_bridge",
  "domain": "rf_bridge",
  "platform": "",
  "renderAs": "root_map",
  "previewGroup": "wireless",
  "helpUrl": "https://esphome.io/components/rf_bridge/",
  "requirements": [
    {
      "require": "bus:uart"
    }
  ],
  "fields": [
    {
      "key": "id",
      "type": "id",
      "required": false,
      "lvl": "simple",
      "placeholder": "rf_bridge_id",
      "idDomain": "rf_bridge"
    },
    {
      "key": "uart_id",
      "type": "id_ref",
      "required": false,
      "lvl": "normal",
      "domain": "uart",
      "placeholder": "uart_bus"
    },
    {
      "key": "on_code_received",
      "type": "list",
      "required": false,
      "lvl": "simple",
      "item": {
        "type": "object",
        "fields": [],
        "extends": "base_actions.json"
      },
      "wrapThen": true
    },
    {
      "key": "on_advanced_code_received",
      "type": "list",
      "required": false,
      "lvl": "normal",
      "item": {
        "type": "object",
        "fields": [],
        "extends": "base_actions.json"
      },
      "wrapThen": true
    },
    {
      "key": "custom_config",
      "type": "raw_yaml",
      "required": false,
      "lvl": "advanced"
    }
  ]
}
