{
  "id": "sensor.qmc5883l",
  "domain": "sensor",
  "platform": "qmc5883l",
  "helpUrl": "https://esphome.io/components/sensor/qmc5883l/",
  "requirements": [
    {
      "require": "bus:i2c"
    }
  ],
  "fields": [
    {
      "key": "address",
      "type": "address",
      "required": false,
      "lvl": "simple",
      "emitYAML": "always",
      "default": "0x0D",
      "placeholder": "0x0D"
    },
    {
      "key": "update_interval",
      "type": "duration",
      "required": false,
      "lvl": "simple",
      "placeholder": "60s"
    },
    {
      "key": "drdy_pin",
      "type": "gpio",
      "required": false,
      "lvl": "normal",
	  "placeholder": "GPIOXX"
    },
    {
      "key": "data_rate",
      "type": "select",
      "required": false,
      "lvl": "normal",
	  "default": "200Hz",
      "options": [
        "200Hz",
        "100Hz",
        "50Hz",
        "10Hz"
      ]
    },
    {
      "key": "range",
      "type": "select",
      "required": false,
      "lvl": "normal",
	  "default": "200uT",
      "options": [
        "200uT",
        "800uT"
      ]
    },
    {
      "key": "oversampling",
      "type": "select",
      "required": false,
      "lvl": "normal",
	  "default": "512x",
      "options": [
        "512x",
        "256x",
        "128x",
        "64x"
      ]
    },
    {
      "key": "custom_config",
      "type": "raw_yaml",
      "required": false,
      "lvl": "advanced"
    },
    {
      "key": "field_strength_x",
      "type": "object",
      "required": false,
      "lvl": "simple",
      "extends": "base_sensor.json",
      "fields": []
    },
    {
      "key": "field_strength_y",
      "type": "object",
      "required": false,
      "lvl": "simple",
      "extends": "base_sensor.json",
      "fields": []
    },
    {
      "key": "field_strength_z",
      "type": "object",
      "required": false,
      "lvl": "simple",
      "extends": "base_sensor.json",
      "fields": []
    },
    {
      "key": "heading",
      "type": "object",
      "required": false,
      "lvl": "simple",
      "extends": "base_sensor.json",
      "fields": []
    },
    {
      "key": "temperature",
      "type": "object",
      "required": false,
      "lvl": "simple",
      "extends": "base_sensor.json",
      "fields": []
    }
  ]
}
