{
  "id": "remote_transmitter.transmit_panasonic",
  "fields": [
    {
      "key": "id",
      "label": "Remote transmitter",
      "type": "id_ref",
      "required": false,
      "placeholder": "remote_transmitter_id",
      "domain": "remote_transmitter",
      "lvl": "normal"
    },
    {
      "key": "address",
      "label": "Address",
      "type": "number",
      "templatable": true,
      "required": true,
      "lvl": "normal",
      "placeholder": "0x4004",
      "lambdaPlaceholder": "return 0x4004;"
    },
    {
      "key": "command",
      "label": "Command",
      "type": "number",
      "templatable": true,
      "required": true,
      "lvl": "normal",
      "placeholder": "0x100BCBD",
      "lambdaPlaceholder": "return 0x100BCBD;"
    },
    {
      "key": "repeat",
      "label": "Repeat",
      "type": "object",
      "required": false,
      "lvl": "advanced",
      "fields": [
        {
          "key": "times",
          "label": "Times",
          "type": "number",
          "templatable": true,
          "required": false,
          "lvl": "normal",
          "placeholder": "2",
          "lambdaPlaceholder": "return 2;"
        },
        {
          "key": "wait_time",
          "label": "Wait time",
          "type": "duration",
          "templatable": true,
          "required": false,
          "lvl": "normal",
          "placeholder": "25ms",
          "lambdaPlaceholder": "return 25;"
        }
      ]
    }
  ]
}
