{
  "id": "sensor.bmi160",
  "domain": "sensor",
  "platform": "bmi160",
  "helpUrl": "https://esphome.io/components/sensor/bmi160/",
  "requirements": [
    {
      "require": "bus:i2c"
    }
  ],
  "fields": [
    {
      "key": "address",
      "type": "select",
      "required": false,
      "lvl": "simple",
      "default": "0x68",
      "emitYAML": "always",
      "options": [
        "0x68",
        "0x69"
      ]
    },
    {
      "key": "id",
      "type": "id",
      "required": false,
      "lvl": "normal",
      "idDomain": "bmi160"
    },
    {
      "key": "update_interval",
      "type": "duration",
      "required": false,
      "lvl": "simple",
      "placeholder": "60s"
    },
    {
      "key": "custom_config",
      "type": "raw_yaml",
      "required": false,
      "lvl": "advanced"
    },
    {
      "key": "acceleration_x",
      "type": "object",
      "required": false,
      "lvl": "simple",
      "extends": "base_sensor.json",
      "fields": []
    },
    {
      "key": "acceleration_y",
      "type": "object",
      "required": false,
      "lvl": "simple",
      "extends": "base_sensor.json",
      "fields": []
    },
    {
      "key": "acceleration_z",
      "type": "object",
      "required": false,
      "lvl": "simple",
      "extends": "base_sensor.json",
      "fields": []
    },
    {
      "key": "gyroscope_x",
      "type": "object",
      "required": false,
      "lvl": "simple",
      "extends": "base_sensor.json",
      "fields": []
    },
    {
      "key": "gyroscope_y",
      "type": "object",
      "required": false,
      "lvl": "simple",
      "extends": "base_sensor.json",
      "fields": []
    },
    {
      "key": "gyroscope_z",
      "type": "object",
      "required": false,
      "lvl": "simple",
      "extends": "base_sensor.json",
      "fields": []
    },
    {
      "key": "temperature",
      "type": "object",
      "required": false,
      "lvl": "simple",
      "extends": "base_sensor.json",
      "fields": []
    }
  ]
}
