{
  "id": "sensor.mpu6886",
  "domain": "sensor",
  "platform": "mpu6886",
  "helpUrl": "https://esphome.io/components/sensor/mpu6886/",
  "extends": "base_sensor.json",
  "requirements": [
    {
      "require": "bus:i2c"
    }
  ],
  "fields": [
    {
      "key": "name",
      "placeholder": "Sensor Name",
      "type": "text",
      "required": true,
      "lvl": "simple"
    },
    {
      "key": "address",
      "type": "address",
      "required": false,
      "lvl": "simple",
      "placeholder": "0x68"
    },
    {
      "key": "accel_x",
      "type": "text",
      "required": false,
      "lvl": "normal"
    },
    {
      "key": "accel_y",
      "type": "text",
      "required": false,
      "lvl": "normal"
    },
    {
      "key": "accel_z",
      "type": "text",
      "required": false,
      "lvl": "normal"
    },
    {
      "key": "gyro_x",
      "type": "text",
      "required": false,
      "lvl": "normal"
    },
    {
      "key": "gyro_y",
      "type": "text",
      "required": false,
      "lvl": "normal"
    },
    {
      "key": "gyro_z",
      "type": "text",
      "required": false,
      "lvl": "normal"
    },
    {
      "key": "temperature",
      "type": "text",
      "required": false,
      "lvl": "normal"
    },
    {
      "key": "update_interval",
      "type": "duration",
      "required": false,
      "lvl": "simple",
      "placeholder": "60s"
    }
  ]
}
