{
  "id": "sensor.xiaomi_miscale",
  "domain": "sensor",
  "platform": "xiaomi_miscale",
  "helpUrl": "https://esphome.io/components/sensor/xiaomi_miscale/",
  "fields": [
    {
      "key": "mac_address",
      "type": "text",
	  "suppressQuotes": true,
      "required": true,
      "lvl": "simple",
	  "placeholder": "XX:XX:XX:XX:XX:XX"
    },
    {
      "key": "clear_impedance",
      "type": "boolean",
      "required": false,
      "lvl": "normal",
	  "note": "Only available on MiScale2"
    },
    {
      "key": "weight",
      "type": "object",
      "required": false,
      "lvl": "simple",
      "extends": "base_sensor.json",
      "fields": []
    },
    {
      "key": "impedance",
      "type": "object",
      "required": false,
      "lvl": "simple",
      "extends": "base_sensor.json",
      "fields": []
    }
  ]
}
