{
  "id": "time.pcf8563",
  "domain": "time",
  "platform": "pcf8563",
  "requires": [
    "i2c"
  ],
  "helpUrl": "https://esphome.io/components/time/pcf8563/",
  "extends": "base_time.json",
  "fields": [
    {
      "key": "address",
      "type": "text",
      "required": false,
      "lvl": "normal",
      "default": "0xA3",
      "suppressQuotes": true
    },
    {
      "key": "i2c_id",
      "type": "id_ref",
      "required": false,
      "lvl": "advanced",
      "domain": "i2c"
    }
  ]
}
